[
  {
    "id": 1,
    "name": "administrator",
    "nice_name": "Administrator",
    "color_hex": "e84c3c",
    "color_minecraft": "4",
    "tag_name": "ADMIN",
    "display_type": "ABOVE_HEAD"
  },
  {
    "id": 2,
    "name": "developer",
    "nice_name": "Developer",
    "color_hex": "e84c3c",
    "color_minecraft": "b",
    "tag_name": "DEV",
    "display_type": "ABOVE_HEAD"
  },
  {
    "id": 3,
    "name": "seniormoderator",
    "nice_name": "Sr Moderator",
    "color_hex": "e84c3c",
    "color_minecraft": "6",
    "tag_name": "SR MOD",
    "display_type": "ABOVE_HEAD"
  },
  {
    "id": 4,
    "name": "moderator",
    "nice_name": "Moderator",
    "color_hex": "e84c3c",
    "color_minecraft": "6",
    "tag_name": "MOD",
    "display_type": "ABOVE_HEAD"
  },
  {
    "id": 6,
    "name": "content",
    "nice_name": "Content",
    "color_hex": "e84c3c",
    "color_minecraft": "2",
    "tag_name": "CONTENT",
    "display_type": "ABOVE_HEAD"
  },
  {
    "id": 12,
    "name": "juniordeveloper",
    "nice_name": "Jr Developer",
    "color_hex": "e84c3c",
    "color_minecraft": "b",
    "tag_name": null,
    "display_type": "NONE"
  },
  {
    "id": 5,
    "name": "juniormoderator",
    "nice_name": "Jr Moderator",
    "color_hex": null,
    "color_minecraft": "6",
    "tag_name": null,
    "display_type": "NONE"
  },
  {
    "id": 11,
    "name": "cosmeticcreator",
    "nice_name": "Cosmetic Creator",
    "color_hex": null,
    "color_minecraft": "f",
    "tag_name": null,
    "display_type": "NONE"
  },
  {
    "id": 7,
    "name": "translator",
    "nice_name": "Translator",
    "color_hex": "50D35F",
    "color_minecraft": "a",
    "tag_name": null,
    "display_type": "BESIDE_NAME"
  },
  {
    "id": 8,
    "name": "partner",
    "nice_name": "Partner",
    "color_hex": "BE00BE",
    "color_minecraft": "5",
    "tag_name": "PARTNER",
    "display_type": "ABOVE_HEAD"
  },
  {
    "id": 9,
    "name": "vip",
    "nice_name": "VIP",
    "color_hex": "BE00BE",
    "color_minecraft": "5",
    "tag_name": null,
    "display_type": "BESIDE_NAME"
  },
  {
    "id": 10,
    "name": "plus",
    "nice_name": "LabyMod+",
    "color_hex": "FFC700",
    "color_minecraft": "e",
    "tag_name": null,
    "display_type": "BESIDE_NAME"
  }
]
